<?xml version='1.0' encoding='utf-8'?>
<mets xmlns:xlink="http://www.w3.org/1999/xlink" xmlns="http://www.loc.gov/METS/">
  <dmdSec ID="case">
    <mdWrap MDTYPE="OTHER" OTHERMDTYPE="HLS-CASELAW-CASEXML">
      <xmlData>
        <case xmlns="http://nrs.harvard.edu/urn-3:HLS.Libr.US_Case_Law.Schema.Case:v1" caseid="NOTALEPH000693_0026" publicationstatus="published">
          <court abbreviation="Ark. Ct. App." jurisdiction="Arkansas">Arkansas Court of Appeals</court>
          <name abbreviation="Office of Child Support Enforcement v. Watkins">OFFICE of CHILD SUPPORT ENFORCEMENT v. Roger Lee WATKINS</name>
          <docketnumber>CA 03-143</docketnumber>
          <citation category="official" type="bluebook">83 Ark. App. 174</citation>
          <citation category="parallel" type="bluebook">119 S.W.3d 74</citation>
          <decisiondate>2003-10-01</decisiondate>
        </case>
      </xmlData>
    </mdWrap>
  </dmdSec>
  <amdSec ID="amd0001">
    <digiprovMD ID="digi001">
      <mdWrap MDTYPE="PREMIS">
        <xmlData>
          <event xmlns="info:lc/xmlns/premis-v2">
            <eventIdentifier>
              <eventIdentifierType>Local</eventIdentifierType>
              <eventIdentifierValue>scn0001</eventIdentifierValue>
            </eventIdentifier>
            <eventType>capture</eventType>
            <eventDateTime>2016-03-22T22:26:39Z</eventDateTime>
            <eventDetail>Scan date noting when printed source volume was converted to digital images used as sources for transcription.</eventDetail>
          </event>
          <agent xmlns="info:lc/xmlns/premis-v2">
            <agentIdentifier>
              <agentIdentifierType>Local</agentIdentifierType>
              <agentIdentifierValue>HLSL</agentIdentifierValue>
            </agentIdentifier>
            <agentName>Harvard Law School Library</agentName>
            <agentType>organization</agentType>
          </agent>
        </xmlData>
      </mdWrap>
    </digiprovMD>
    <digiprovMD ID="digi002">
      <mdWrap MDTYPE="PREMIS">
        <xmlData>
          <event xmlns="info:lc/xmlns/premis-v2">
            <eventIdentifier>
              <eventIdentifierType>Local</eventIdentifierType>
              <eventIdentifierValue>ocr0001</eventIdentifierValue>
            </eventIdentifier>
            <eventType>transcription</eventType>
            <eventDateTime>2017-06-27T16:18:02Z</eventDateTime>
            <eventDetail>Transcription event</eventDetail>
          </event>
          <agent xmlns="info:lc/xmlns/premis-v2">
            <agentIdentifier>
              <agentIdentifierType>Local</agentIdentifierType>
              <agentIdentifierValue>dsrs</agentIdentifierValue>
            </agentIdentifier>
            <agentName>Innodata DSRS, ABBYY FineReader</agentName>
            <agentType>software</agentType>
            <agentNote>Version 10</agentNote>
          </agent>
        </xmlData>
      </mdWrap>
    </digiprovMD>
    <digiprovMD ID="digi003">
      <mdWrap MDTYPE="PREMIS">
        <xmlData>
          <event xmlns="info:lc/xmlns/premis-v2">
            <eventIdentifier>
              <eventIdentifierType>Local</eventIdentifierType>
              <eventIdentifierValue>crt0001</eventIdentifierValue>
            </eventIdentifier>
            <eventType>METScreation</eventType>
            <eventDateTime>2017-07-28T10:06:25Z</eventDateTime>
            <eventDetail>Creation of digital artifact described by this METS file</eventDetail>
          </event>
          <agent xmlns="info:lc/xmlns/premis-v2">
            <agentIdentifier>
              <agentIdentifierType>Local</agentIdentifierType>
              <agentIdentifierValue>redrli</agentIdentifierValue>
            </agentIdentifier>
            <agentName>Innodata R.E.D. Workbench/RLI tool</agentName>
            <agentType>software</agentType>
            <agentNote>Version 20170726.post182</agentNote>
          </agent>
        </xmlData>
      </mdWrap>
    </digiprovMD>
    <digiprovMD ID="digi004">
      <mdWrap MDTYPE="PREMIS">
        <xmlData>
          <event xmlns="info:lc/xmlns/premis-v2">
            <eventIdentifier>
              <eventIdentifierType>Local</eventIdentifierType>
              <eventIdentifierValue>red0001</eventIdentifierValue>
            </eventIdentifier>
            <eventType>redaction</eventType>
            <eventDateTime>2017-07-28T10:08:27Z</eventDateTime>
            <eventDetail>Redaction step</eventDetail>
          </event>
          <agent xmlns="info:lc/xmlns/premis-v2">
            <agentIdentifier>
              <agentIdentifierType>Local</agentIdentifierType>
              <agentIdentifierValue>redravel-redactor</agentIdentifierValue>
            </agentIdentifier>
            <agentName>Innodata R.E.D. Workbench/RLI tool</agentName>
            <agentType>software</agentType>
            <agentNote>Version 20170726.post182</agentNote>
          </agent>
        </xmlData>
      </mdWrap>
    </digiprovMD>
  </amdSec>
  <fileSec>
    <fileGrp USE="tiff">
      <file ID="tiff_00100_1" MIMETYPE="image/tiff" CHECKSUM="0ed94da18fee1bccccaebb05f1b90fa2" CHECKSUMTYPE="MD5" SIZE="8338">
        <FLocat LOCTYPE="URL" xlink:href="../images/NOTALEPH000693_00100_1.tif"/>
      </file>
      <file ID="tiff_00101_0" MIMETYPE="image/tiff" CHECKSUM="393706d91fcd078208a06a8d09d39030" CHECKSUMTYPE="MD5" SIZE="32702">
        <FLocat LOCTYPE="URL" xlink:href="../images/NOTALEPH000693_00101_0.tif"/>
      </file>
      <file ID="tiff_00101_1" MIMETYPE="image/tiff" CHECKSUM="61bcfa34b5006894899a161a62c5af8a" CHECKSUMTYPE="MD5" SIZE="54062">
        <FLocat LOCTYPE="URL" xlink:href="../images/NOTALEPH000693_00101_1.tif"/>
      </file>
      <file ID="tiff_00102_0" MIMETYPE="image/tiff" CHECKSUM="047b855fee42a64ba313665c9c70f74e" CHECKSUMTYPE="MD5" SIZE="58192">
        <FLocat LOCTYPE="URL" xlink:href="../images/NOTALEPH000693_00102_0.tif"/>
      </file>
      <file ID="tiff_00102_1" MIMETYPE="image/tiff" CHECKSUM="c6f1e8e6fea8b725e86a472cdfa063fe" CHECKSUMTYPE="MD5" SIZE="31452">
        <FLocat LOCTYPE="URL" xlink:href="../images/NOTALEPH000693_00102_1.tif"/>
      </file>
    </fileGrp>
    <fileGrp USE="jp2">
      <file ID="jp2_00100_1" MIMETYPE="image/jp2" CHECKSUM="a089accda777f17a1e1aa9b6d43b0dfc" CHECKSUMTYPE="MD5" SIZE="1524055">
        <FLocat LOCTYPE="URL" xlink:href="../images/NOTALEPH000693_00100_1.jp2"/>
      </file>
      <file ID="jp2_00101_0" MIMETYPE="image/jp2" CHECKSUM="ab7194320a0bb444349b3b2a992280b7" CHECKSUMTYPE="MD5" SIZE="2100205">
        <FLocat LOCTYPE="URL" xlink:href="../images/NOTALEPH000693_00101_0.jp2"/>
      </file>
      <file ID="jp2_00101_1" MIMETYPE="image/jp2" CHECKSUM="a6a0138bcec5f39a32b7b19b9910f363" CHECKSUMTYPE="MD5" SIZE="2641607">
        <FLocat LOCTYPE="URL" xlink:href="../images/NOTALEPH000693_00101_1.jp2"/>
      </file>
      <file ID="jp2_00102_0" MIMETYPE="image/jp2" CHECKSUM="905610b76904de890147651e6daf0481" CHECKSUMTYPE="MD5" SIZE="2670606">
        <FLocat LOCTYPE="URL" xlink:href="../images/NOTALEPH000693_00102_0.jp2"/>
      </file>
      <file ID="jp2_00102_1" MIMETYPE="image/jp2" CHECKSUM="0098e4ddcd03a3d80e7a833728719809" CHECKSUMTYPE="MD5" SIZE="2452150">
        <FLocat LOCTYPE="URL" xlink:href="../images/NOTALEPH000693_00102_1.jp2"/>
      </file>
    </fileGrp>
    <fileGrp USE="alto">
      <file ID="alto_00100_1" MIMETYPE="text/xml" CHECKSUM="8e92ff2a3cea94a91fc38fa520d293ed" CHECKSUMTYPE="MD5" SIZE="8527">
        <FLocat LOCTYPE="URL" xlink:href="../alto/NOTALEPH000693_redacted_ALTO_00100_1.xml"/>
      </file>
      <file ID="alto_00101_0" MIMETYPE="text/xml" CHECKSUM="8084cd5c67b9ba2d898557cb4c276e04" CHECKSUMTYPE="MD5" SIZE="52598">
        <FLocat LOCTYPE="URL" xlink:href="../alto/NOTALEPH000693_redacted_ALTO_00101_0.xml"/>
      </file>
      <file ID="alto_00101_1" MIMETYPE="text/xml" CHECKSUM="36a2bbb497ade13b7208d9742245d44e" CHECKSUMTYPE="MD5" SIZE="89892">
        <FLocat LOCTYPE="URL" xlink:href="../alto/NOTALEPH000693_redacted_ALTO_00101_1.xml"/>
      </file>
      <file ID="alto_00102_0" MIMETYPE="text/xml" CHECKSUM="b1ea08cf755d0a9c74a4b0754758b5d8" CHECKSUMTYPE="MD5" SIZE="98054">
        <FLocat LOCTYPE="URL" xlink:href="../alto/NOTALEPH000693_redacted_ALTO_00102_0.xml"/>
      </file>
      <file ID="alto_00102_1" MIMETYPE="text/xml" CHECKSUM="791b1a606b72f2d71e171da7f07ee45e" CHECKSUMTYPE="MD5" SIZE="50906">
        <FLocat LOCTYPE="URL" xlink:href="../alto/NOTALEPH000693_redacted_ALTO_00102_1.xml"/>
      </file>
    </fileGrp>
    <fileGrp USE="casebody">
      <file ID="casebody_0026" MIMETYPE="text/xml">
        <FContent>
          <xmlData>
            <casebody xmlns="http://nrs.harvard.edu/urn-3:HLS.Libr.US_Case_Law.Schema.Case_Body:v1" firstpage="174" lastpage="178">
              <court id="b200-5" pgmap="200">Court of Appeals of Arkansas Division I</court>
              <docketnumber id="b200-4" pgmap="200">CA 03-143</docketnumber>
              <citation id="A7c" pgmap="200">119 S.W.3d 74</citation>
              <parties id="b200-3" pgmap="200">OFFICE of CHILD SUPPORT ENFORCEMENT v. Roger Lee WATKINS</parties>
              <decisiondate id="b200-6" pgmap="200">Opinion delivered October 1, 2003</decisiondate>
              <judges id="b204-8" pgmap="204">Griffen and Neal, JJ., agree.</judges>
              <attorneys id="b201-8" pgmap="201">David B. Alexander, for appellant.</attorneys>
              <opinion type="majority">
                <author id="b201-9" pgmap="201">ohn B. Robbins, Judge.</author>
                <p id="Ac0z" pgmap="201">Appellee Roger Lee Watkins and Karla Watkins are the parents of a minor child, Brandon. On November 4,1997, a hearing was held on a motion by the appellant, Office of Child Support Enforcement (OCSE), against Mr. Watkins. Subsequent to the hearing, the trial court entered a judgment against Mr. Watkins for $2082.50, which represented unpaid child support owed to the state of Missouri. The debt accrued as a result of an assignment of child-support rights to the State of Missouri by Ms. Watkins upon her receipt of public assistance. The November 4, 1997, order further required Mr. Watkins to pay current child support.</p>
                <p id="b201-13" pgmap="201">In an order dated July 6, 1998, the trial court found Ms. Watkins in contempt for denying visitation, and placed temporary custody with Mr. Watkins. On October 6, 1998, the trial court entered an order granting permanent custody to Mr. Watkins, and Ms. Watkins was ordered to pay child support. The order recited that Ms. Watkins shall be given credit toward her child-support obligation for any arrears owed by Mr. Watkins.</p>
                <p id="b201-14" pgmap="201(31) 202(24)">On July 8, 2002, the trial court entered an order finding Ms. Watkins in contempt based on her child-support delinquency of at least $5300.00. OCSE subsequently intervened and filed a motion for citation against Mr. Watkins for failure to pay the 1997 judgment, and a hearing was held on its motion on August 14, 2002.</p>
                <p id="b202-6" pgmap="202">The hearing on appellant’s motion consisted only of stipu­lations and argument by each party’s counsel. On October 21, 2002, the trial court entered an order denying appellant’s motion for citation. In its order, the trial court found that Mr. Watkins made only one payment toward the judgment and still owed $2032.50. However, the trial court chose not to enforce the judgment against Mr. Watkins. The trial court’s order, in pertinent part, stated:</p>
                <blockquote id="b202-7" pgmap="202">[T]he Court finds that the Plaintiff, Karla Jeen Watkins, is over $6,000.00 in arrears to the Defendant, Roger Lee Watkins, in child support. That the Court applies the equitable doctrine of set-off and therefore estops the Intervenor from collecting the outstanding balance of $2,032.50 from the Defendant, Roger Lee Watkins. That even though Karlajeen Watkins assigned her support rights to the State of Missouri, the State of Missouri does not acquire any greater claim as assignee to back support than what Karla Jeen Watkins possesses herself.</blockquote>
                <blockquote id="b202-8" pgmap="202">Further, that the Court acknowledges that the Plaintiff, Karla Jeen Watkins, was provided a credit towards child support obligation for an arrearage due and owing by the Defendant, Roger Lee Watkins, but, had accepted funds from the State of Missouri, and therefore, her credit is abrogated for any amounts due and owing the State of Missouri as she was not entitled to ofiset the debt owed to the State of Missouri.</blockquote>
                <p id="b202-9" pgmap="202">OCSE now appeals from the order entered October 21, 2002.</p>
                <p id="b202-10" pgmap="202(115) 203(29)">For reversal, OCSE acknowledged that Arkansas Code An­notated section 16-65-603(a) (1987) provides, “Judgments for the recovery of money may be set off against each other, having due regard to the legal and equitable rights of all persons interested in both judgments.” However, OCSE argues that it is inequitable to allow the judgment owed by Mr. Watkins to the State of Missouri to be set off against Ms. Watkins’s child-support arrearage. OCSE submits that Ms. Watkins has no interest in the judgment granted to Missouri, nor does Missouri share in her liability to Mr. Watkins. OCSE contends that the trial court’s reasoning depended on the assignment of Ms. Watkins’s rights to the State of Missouri, and that the reasoning was flawed because the judgment itself was not an assignment; rather, it was a judicial determination of Mr. Watkins’s obligation to the State of Missouri.</p>
                <p id="b203-4" pgmap="203">
                   OCSE agrees that an assignee ordinarily obtains only the rights possessed by the assignor at the time of the assignment, and no more. 6A C.J.S. Assignments § 88 (1975); See First Nat’l Bank of Fayetteville v. Massachusetts Gen. Life Ins. Co., 296 Ark. 28, 752 S.W.2d 1 (1988). However, it argues that collection of the judgment by the assignee in this case should not be barred because the assignment and entry of judgment both occurred prior to any child-support obligation on the part of Ms. Watkins. Since the set-off defense was not available to Mr. Watkins against the assignor at the time of the assignment, OCSE contends it should not be now available against the assignee. The general rule is that the assignee of a chose in action is ordinarily subject to any setoff or counterclaim available to the obligor against the assignor, and to all other defenses and equities that could have been asserted against the assignor at the time of the assignment (emphasis added). 6 Am. Jur. 2D Assignments § 149 (1999).</p>
                <p id="b203-5" pgmap="203">
                   The standard of review of a circuit court’s finding following a bench trial is whether that finding was clearly errone­ous. City of Fort Smith v. River Valley Reg’l Water Dist., 344 Ark. 57, 37 S.W.3d 631 (2001). However, a trial court’s conclusion of law is not entitled to the same deference. See Duchac v. City of Hot Springs, 67 Ark. App. 98, 992 S.W.2d 174 (1999). We hold that under the particular facts of this case, the trial court erred as a matter of law in ruling that the set-off doctrine estops OCSE from collecting the outstanding judgment of $2032.50 from Mr. Wat­kins.</p>
                <p id="b203-6" pgmap="203(108) 204(39)">
                   Because Ms. Watkins was receiving public assistance while she resided in Missouri with the child, her child-support rights were assigned to the State of Missouri by operation of law. See Mo. Ann. Stat. § 208.055 (2002). Pursuant to Missouri Annotated Statutes section 454.410 (2002), support rights assigned to the state shall constitute an obligation owed to the state by the person responsible for providing such support, and the obligation shall be collectible pursuant to all legal processes. Through legal process, OCSE obtained a judgment against Mr. Watkins for unpaid child support, and Mr. Watkins took no appeal from the judgment. Significantly, Ms. Watkins’s assignment of her rights to Missouri was not a voluntary assignment for her benefit, but by operation of law due to her receipt of public assistance for her minor child. Thus, collection on the judgment is a matter strictly between Missouri and Mr. Watkins.</p>
                <p id="b204-5" pgmap="204">
                   In this case, Mr. Watkins has no right to set off the judgment owed to the State of Missouri against the child-support arrearages owed to him by Ms. Watkins. At both the time of assignment and entry of the judgment, Ms. Watkins owed nothing to Mr. Watkins and thus, absent the assignment, Ms. Watkins would have had the right to collect on the judgment. As Mr. Watkins would have had no set-off defense against Ms. Watkins, he cannot now assert the defense against the assignee, State of Missouri. The fact that Ms. Watkins later became delinquent on her child-support obligation to Mr. Watkins does not affect the State of Missouri’s right to collection on its judgment.</p>
                <p id="b204-6" pgmap="204">We reverse the trial court’s order to the extent that it estops OCSE from collecting the outstanding balance on the judgment against Mr. Watkins. We remand the case to the trial court for reconsideration of OCSE’s motion for citation against Mr. Wat­kins in light of our holding.</p>
                <p id="b204-7" pgmap="204">Reversed and remanded.</p>
              </opinion>
            </casebody>
          </xmlData>
        </FContent>
      </file>
    </fileGrp>
  </fileSec>
  <structMap TYPE="physical">
    <div TYPE="volume">
      <div ORDER="200" ORDERLABEL="174" TYPE="page">
        <fptr FILEID="tiff_00100_1"/>
        <fptr FILEID="jp2_00100_1"/>
        <fptr FILEID="alto_00100_1"/>
        <div TYPE="pagelabel">
          <fptr>
            <seq>
              <area BEGIN="BL_200.1" BETYPE="IDREF" FILEID="alto_00100_1"/>
            </seq>
          </fptr>
        </div>
      </div>
      <div ORDER="201" ORDERLABEL="175" TYPE="page">
        <fptr FILEID="tiff_00101_0"/>
        <fptr FILEID="jp2_00101_0"/>
        <fptr FILEID="alto_00101_0"/>
        <div TYPE="pagelabel">
          <fptr>
            <seq>
              <area BEGIN="BL_201.1" BETYPE="IDREF" FILEID="alto_00101_0"/>
            </seq>
          </fptr>
        </div>
      </div>
      <div ORDER="202" ORDERLABEL="176" TYPE="page">
        <fptr FILEID="tiff_00101_1"/>
        <fptr FILEID="jp2_00101_1"/>
        <fptr FILEID="alto_00101_1"/>
        <div TYPE="pagelabel">
          <fptr>
            <seq>
              <area BEGIN="BL_202.2" BETYPE="IDREF" FILEID="alto_00101_1"/>
            </seq>
          </fptr>
        </div>
      </div>
      <div ORDER="203" ORDERLABEL="177" TYPE="page">
        <fptr FILEID="tiff_00102_0"/>
        <fptr FILEID="jp2_00102_0"/>
        <fptr FILEID="alto_00102_0"/>
        <div TYPE="pagelabel">
          <fptr>
            <seq>
              <area BEGIN="BL_203.2" BETYPE="IDREF" FILEID="alto_00102_0"/>
            </seq>
          </fptr>
        </div>
      </div>
      <div ORDER="204" ORDERLABEL="178" TYPE="page">
        <fptr FILEID="tiff_00102_1"/>
        <fptr FILEID="jp2_00102_1"/>
        <fptr FILEID="alto_00102_1"/>
        <div TYPE="pagelabel">
          <fptr>
            <seq>
              <area BEGIN="BL_204.2" BETYPE="IDREF" FILEID="alto_00102_1"/>
            </seq>
          </fptr>
        </div>
      </div>
    </div>
  </structMap>
  <structMap TYPE="xref">
    <div TYPE="blocks">
      <div TYPE="element">
        <fptr>
          <area BEGIN="b200-4" BETYPE="IDREF" FILEID="casebody_0026"/>
        </fptr>
        <fptr>
          <seq>
            <area BEGIN="BL_200.4" BETYPE="IDREF" FILEID="alto_00100_1"/>
          </seq>
        </fptr>
      </div>
      <div TYPE="element">
        <fptr>
          <area BEGIN="b200-5" BETYPE="IDREF" FILEID="casebody_0026"/>
        </fptr>
        <fptr>
          <seq>
            <area BEGIN="BL_200.6" BETYPE="IDREF" FILEID="alto_00100_1"/>
          </seq>
        </fptr>
      </div>
      <div TYPE="element">
        <fptr>
          <area BEGIN="b200-6" BETYPE="IDREF" FILEID="casebody_0026"/>
        </fptr>
        <fptr>
          <seq>
            <area BEGIN="BL_200.7" BETYPE="IDREF" FILEID="alto_00100_1"/>
          </seq>
        </fptr>
      </div>
      <div TYPE="element">
        <fptr>
          <area BEGIN="b202-6" BETYPE="IDREF" FILEID="casebody_0026"/>
        </fptr>
        <fptr>
          <seq>
            <area BEGIN="BL_202.5" BETYPE="IDREF" FILEID="alto_00101_1"/>
          </seq>
        </fptr>
      </div>
      <div TYPE="element">
        <fptr>
          <area BEGIN="b202-7" BETYPE="IDREF" FILEID="casebody_0026"/>
        </fptr>
        <fptr>
          <seq>
            <area BEGIN="BL_202.6" BETYPE="IDREF" FILEID="alto_00101_1"/>
          </seq>
        </fptr>
      </div>
      <div TYPE="element">
        <fptr>
          <area BEGIN="b200-3" BETYPE="IDREF" FILEID="casebody_0026"/>
        </fptr>
        <fptr>
          <seq>
            <area BEGIN="BL_200.3" BETYPE="IDREF" FILEID="alto_00100_1"/>
          </seq>
        </fptr>
      </div>
      <div TYPE="element">
        <fptr>
          <area BEGIN="b202-8" BETYPE="IDREF" FILEID="casebody_0026"/>
        </fptr>
        <fptr>
          <seq>
            <area BEGIN="BL_202.7" BETYPE="IDREF" FILEID="alto_00101_1"/>
          </seq>
        </fptr>
      </div>
      <div TYPE="element">
        <fptr>
          <area BEGIN="b202-9" BETYPE="IDREF" FILEID="casebody_0026"/>
        </fptr>
        <fptr>
          <seq>
            <area BEGIN="BL_202.8" BETYPE="IDREF" FILEID="alto_00101_1"/>
          </seq>
        </fptr>
      </div>
      <div TYPE="element">
        <fptr>
          <area BEGIN="b204-6" BETYPE="IDREF" FILEID="casebody_0026"/>
        </fptr>
        <fptr>
          <seq>
            <area BEGIN="BL_204.6" BETYPE="IDREF" FILEID="alto_00102_1"/>
          </seq>
        </fptr>
      </div>
      <div TYPE="element">
        <fptr>
          <area BEGIN="b204-5" BETYPE="IDREF" FILEID="casebody_0026"/>
        </fptr>
        <fptr>
          <seq>
            <area BEGIN="BL_204.5" BETYPE="IDREF" FILEID="alto_00102_1"/>
          </seq>
        </fptr>
      </div>
      <div TYPE="element">
        <fptr>
          <area BEGIN="b201-9" BETYPE="IDREF" FILEID="casebody_0026"/>
        </fptr>
        <fptr>
          <seq>
            <area BEGIN="BL_201.10" BETYPE="IDREF" FILEID="alto_00101_0"/>
          </seq>
        </fptr>
      </div>
      <div TYPE="element">
        <fptr>
          <area BEGIN="b201-8" BETYPE="IDREF" FILEID="casebody_0026"/>
        </fptr>
        <fptr>
          <seq>
            <area BEGIN="BL_201.9" BETYPE="IDREF" FILEID="alto_00101_0"/>
          </seq>
        </fptr>
      </div>
      <div TYPE="element">
        <fptr>
          <area BEGIN="b203-6" BETYPE="IDREF" FILEID="casebody_0026"/>
        </fptr>
        <fptr>
          <seq>
            <area BEGIN="BL_203.6" BETYPE="IDREF" FILEID="alto_00102_0"/>
            <area BEGIN="BL_204.1" BETYPE="IDREF" FILEID="alto_00102_1"/>
          </seq>
        </fptr>
      </div>
      <div TYPE="element">
        <fptr>
          <area BEGIN="A7c" BETYPE="IDREF" FILEID="casebody_0026"/>
        </fptr>
        <fptr>
          <seq>
            <area BEGIN="BL_200.5" BETYPE="IDREF" FILEID="alto_00100_1"/>
          </seq>
        </fptr>
      </div>
      <div TYPE="element">
        <fptr>
          <area BEGIN="b203-5" BETYPE="IDREF" FILEID="casebody_0026"/>
        </fptr>
        <fptr>
          <seq>
            <area BEGIN="BL_203.5" BETYPE="IDREF" FILEID="alto_00102_0"/>
          </seq>
        </fptr>
      </div>
      <div TYPE="element">
        <fptr>
          <area BEGIN="b203-4" BETYPE="IDREF" FILEID="casebody_0026"/>
        </fptr>
        <fptr>
          <seq>
            <area BEGIN="BL_203.4" BETYPE="IDREF" FILEID="alto_00102_0"/>
          </seq>
        </fptr>
      </div>
      <div TYPE="element">
        <fptr>
          <area BEGIN="b201-13" BETYPE="IDREF" FILEID="casebody_0026"/>
        </fptr>
        <fptr>
          <seq>
            <area BEGIN="BL_201.13" BETYPE="IDREF" FILEID="alto_00101_0"/>
          </seq>
        </fptr>
      </div>
      <div TYPE="element">
        <fptr>
          <area BEGIN="Ac0z" BETYPE="IDREF" FILEID="casebody_0026"/>
        </fptr>
        <fptr>
          <seq>
            <area BEGIN="BL_201.11" BETYPE="IDREF" FILEID="alto_00101_0"/>
            <area BEGIN="BL_201.12" BETYPE="IDREF" FILEID="alto_00101_0"/>
          </seq>
        </fptr>
      </div>
      <div TYPE="element">
        <fptr>
          <area BEGIN="b201-14" BETYPE="IDREF" FILEID="casebody_0026"/>
        </fptr>
        <fptr>
          <seq>
            <area BEGIN="BL_201.14" BETYPE="IDREF" FILEID="alto_00101_0"/>
            <area BEGIN="BL_202.1" BETYPE="IDREF" FILEID="alto_00101_1"/>
          </seq>
        </fptr>
      </div>
      <div TYPE="element">
        <fptr>
          <area BEGIN="b202-10" BETYPE="IDREF" FILEID="casebody_0026"/>
        </fptr>
        <fptr>
          <seq>
            <area BEGIN="BL_202.9" BETYPE="IDREF" FILEID="alto_00101_1"/>
            <area BEGIN="BL_203.1" BETYPE="IDREF" FILEID="alto_00102_0"/>
          </seq>
        </fptr>
      </div>
      <div TYPE="element">
        <fptr>
          <area BEGIN="b204-7" BETYPE="IDREF" FILEID="casebody_0026"/>
        </fptr>
        <fptr>
          <seq>
            <area BEGIN="BL_204.7" BETYPE="IDREF" FILEID="alto_00102_1"/>
          </seq>
        </fptr>
      </div>
      <div TYPE="element">
        <fptr>
          <area BEGIN="b204-8" BETYPE="IDREF" FILEID="casebody_0026"/>
        </fptr>
        <fptr>
          <seq>
            <area BEGIN="BL_204.8" BETYPE="IDREF" FILEID="alto_00102_1"/>
          </seq>
        </fptr>
      </div>
    </div>
  </structMap>
</mets>
